odoo10_addon_intrastat_base-10.0.1.2.0-nspkg.pth
odoo/addons/intrastat_base/README.rst
odoo/addons/intrastat_base/__init__.py
odoo/addons/intrastat_base/__manifest__.py
odoo/addons/intrastat_base/data/country_data.xml
odoo/addons/intrastat_base/demo/intrastat_demo.xml
odoo/addons/intrastat_base/i18n/intrastat_base.pot
odoo/addons/intrastat_base/migrations/10.0.1.2.0/post-migration.py
odoo/addons/intrastat_base/models/__init__.py
odoo/addons/intrastat_base/models/account_config_settings.py
odoo/addons/intrastat_base/models/account_tax.py
odoo/addons/intrastat_base/models/intrastat_common.py
odoo/addons/intrastat_base/models/product_template.py
odoo/addons/intrastat_base/models/res_company.py
odoo/addons/intrastat_base/models/res_country.py
odoo/addons/intrastat_base/static/description/icon.png
odoo/addons/intrastat_base/views/account_config_settings.xml
odoo/addons/intrastat_base/views/account_tax.xml
odoo/addons/intrastat_base/views/intrastat.xml
odoo/addons/intrastat_base/views/product_template.xml
odoo/addons/intrastat_base/views/res_country.xml
odoo/addons/intrastat_base/views/res_partner.xml
odoo10_addon_intrastat_base-10.0.1.2.0.dist-info/METADATA
odoo10_addon_intrastat_base-10.0.1.2.0.dist-info/WHEEL
odoo10_addon_intrastat_base-10.0.1.2.0.dist-info/namespace_packages.txt
odoo10_addon_intrastat_base-10.0.1.2.0.dist-info/top_level.txt
odoo10_addon_intrastat_base-10.0.1.2.0.dist-info/RECORD
